rx/__init__.py
rx/__main__.py
rx/doctor.py
rx/report.py
rx/request.py
rx/test_report.py
rx/test_request.py
rx/test_timer.py
rx/timer.py
rx/check/__init__.py
rx/check/check_headers.py
rx/check/test_check.py
rx/check/test_check_headers.py
http_rx-0.5.0.dist-info/LICENSE
http_rx-0.5.0.dist-info/METADATA
http_rx-0.5.0.dist-info/WHEEL
http_rx-0.5.0.dist-info/top_level.txt
http_rx-0.5.0.dist-info/RECORD
