Metadata-Version: 2.1
Name: http-rx
Version: 0.5.0
Summary: Extensible HTTP health checker for Python
Home-page: https://github.com/zcking/http_rx
Author: Zachary King
Author-email: kingzach77@gmail.com
License: UNKNOWN
Platform: UNKNOWN
Classifier: Programming Language :: Python :: 3
Classifier: License :: OSI Approved :: MIT License
Classifier: Operating System :: OS Independent
Classifier: Topic :: Internet :: WWW/HTTP
Classifier: Topic :: Internet :: WWW/HTTP :: Site Management :: Link Checking
Requires-Python: >=3.4
Requires-Dist: certifi (==2019.11.28)
Requires-Dist: chardet (==3.0.4)
Requires-Dist: coverage (==5.0.3)
Requires-Dist: idna (==2.8)
Requires-Dist: pytest (==5.3.5)
Requires-Dist: requests (==2.22.0)
Requires-Dist: urllib3 (==1.25.7)
